LICENSE
README.md
setup.py
umj_framework_py_ex.egg-info/PKG-INFO
umj_framework_py_ex.egg-info/SOURCES.txt
umj_framework_py_ex.egg-info/dependency_links.txt
umj_framework_py_ex.egg-info/requires.txt
umj_framework_py_ex.egg-info/top_level.txt
umj_framowrk/__init__.py
umj_framowrk/examples/example_project.py
umj_framowrk/kernel/builder.py
umj_framowrk/kernel/common.py
umj_framowrk/kernel/interpreter.py