Metadata-Version: 2.1
Name: umj-framework-py-ex
Version: 1.0.1a7
Summary: A simple dinamic UI aiogram extension. Will be much more powered in future.
Home-page: https://github.com/Waffe-Wafle/dynamic_py_loader
Author: Waffe-Wafle
License: MIT
Classifier: Programming Language :: Python :: 3
Classifier: License :: OSI Approved :: MIT License
Classifier: Operating System :: OS Independent
Requires-Python: >=3.6
License-File: LICENSE
